include/box2d/base.h
include/box2d/box2d.h
include/box2d/collision.h
include/box2d/id.h
include/box2d/math_functions.h
include/box2d/types.h
lib/box2d.lib
lib/cmake/box2d/box2dConfig-release.cmake
lib/cmake/box2d/box2dConfig.cmake
lib/cmake/box2d/box2dConfigVersion.cmake
pyb2d3/__init__.py
pyb2d3/_pyb2d3.cp310-win_amd64.pyd
pyb2d3/_pyb2d3.cp311-win_amd64.pyd
pyb2d3/_pyb2d3.cp39-win_amd64.pyd
pyb2d3-0.11.1.dist-info/METADATA
pyb2d3-0.11.1.dist-info/WHEEL
pyb2d3-0.11.1.dist-info/licenses/LICENSE
pyb2d3-0.11.1.dist-info/licenses/extra_licenses/LICENSE_BOX2D
pyb2d3-0.11.1.dist-info/licenses/extra_licenses/LICENSE_NANOBIND
pyb2d3-0.11.1.dist-info/RECORD
