Metadata-Version: 2.4
Name: pyb2d3
Version: 0.11.1
Summary: python box2d bindings for box2d >= 3.1
License-Expression: MIT
License-File: extra_licenses/LICENSE_BOX2D
License-File: extra_licenses/LICENSE_NANOBIND
License-File: LICENSE
Classifier: Programming Language :: Python :: 3.9
Classifier: Programming Language :: Python :: 3.10
Classifier: Programming Language :: Python :: 3.11
Classifier: Programming Language :: Python :: 3.12
Classifier: Programming Language :: Python :: 3.13
Requires-Python: >=3.9
Requires-Dist: numpy
Provides-Extra: frontend
Provides-Extra: frontend-pygame
Requires-Dist: pygame; extra == "frontend-pygame"
Provides-Extra: frontend-opengl
Requires-Dist: PyOpenGL; extra == "frontend-opengl"
Requires-Dist: PyOpenGL_accelerate; extra == "frontend-opengl"
Requires-Dist: imgui-bundle; extra == "frontend-opengl"
Provides-Extra: frontend-ipycanvas
Requires-Dist: ipycanvas; extra == "frontend-ipycanvas"
